{
  "$schema": "https://mintlify.com/schema.json",
  "analytics": {
    "plausible": {
        "domain": "driving-tests.org"
                  }
    },
    "feedback.thumbsRating": true,
  "name": "Driver's Academy | Driving-Tests.org",
  "logo": {
    "dark": "/logo/dt-small-fill.svg",
    "light": "/logo/dt-small-fill.svg"
  },
  "favicon": "/dto-favicon.svg",
  "colors": {
    "primary": "#007AFF",
    "light": "#007AFF",
    "dark": "#007AFF",
    "anchors": {
      "from": "#0D9373",
      "to": "#07C983"
    }
  },
  "topbarLinks": [
    {
      "name": "Back to main site",
      "url": "https://driving-tests.org"
    }
  ],
  "topbarCtaButton": {
    "name": "Pass the first time",
    "url": "https://driving-tests.org/premium/"
  },
  "primaryTab": {
    "name": "Home"
  },
  "tabs": [
    {
      "name": "How-to articles",
      "url": "articles"
    },
    {
      "name": "DMV practice tests",
      "url": "https://driving-tests.org/dmv-practice-test/"
    },
    {
      "name": "CDL manual",
      "url": "https://driving-tests.org/cdl-handbooks/"
    }
  ],
 "navigation": [
  {
    "group": "Start Driving",
    "pages": [
      "start-driving/introduction",
      {
        "group": "Driving Basics",
        "pages": [
          "start-driving/driving-basics",
          "start-driving/knowledge-test",
          "start-driving/road-rules"
        ]
      }
    ]
  },
  {
    "group": "Drive Better",
    "pages": [
      "drive-better/introduction",
      {
        "group": "Safety Tips",
        "pages": [
          "drive-better/introduction"
        ]
      }
    ]
  },

  {
  "group": "Car Care",
  "pages": [
    "car-care/introduction",
    {
      "group": "Routine Maintenance",
      "pages": [
        "car-care/introduction"
      ]
    }
  ]
},
  {
    "group": "On the Road",
    "pages": [
       {
      "group": "Travel Guides",
      "pages": [
        "on-the-road/introduction"
          ]
        },

        {
        "group": "Practical exams",
        "pages": [
          "on-the-road/introduction"
        ]
      },
         "essentials/tsa-background-check",
         "essentials/retake-policy"
    ]
  },
  {
    "group": "Car Buying Tips",
    "pages": [
      "on-the-road/introduction"
    ]
  },
  {
    "group": "Lifestyle and Culture",
    "pages": [
      "on-the-road/introduction"
    ]
  },
  {
      "group": "CDL how-to guides",
      "pages": [
        "articles/start",
        "articles/become-owner-operator",
        "articles/truck-owner-operator"
      ]
    }
],
  "footerSocials": {
    "twitter": "https://twitter.com/driving_tests"
  }
}
